code_simplify/__init__.py
code_simplify/crud/__init__.py
code_simplify/crud/rdb.py
code_simplify/http_utils/__init__.py
code_simplify/http_utils/http_request.py
code_simplify/log/__init__.py
code_simplify/log/logger.py
code_simplify/models/__init__.py
code_simplify/models/base.py
code_simplify/models/errors.py
code_simplify-1.2.4.dist-info/LICENSE
code_simplify-1.2.4.dist-info/METADATA
code_simplify-1.2.4.dist-info/WHEEL
code_simplify-1.2.4.dist-info/top_level.txt
code_simplify-1.2.4.dist-info/RECORD
