Metadata-Version: 2.2
Name: code-simplify
Version: 1.2.4
Summary: A python tool library that covers a wide range of common tools to simplify your work and reduce repetitive code.
Home-page: https://github.com/Yaocool/code-simplify
Author: Ozzy
Author-email: ozzycharon@gmail.com
License: MIT
Keywords: python,http utils,logger utils
License-File: LICENSE
Requires-Dist: aiohttp
Requires-Dist: pydantic
Requires-Dist: SQLAlchemy
Dynamic: author
Dynamic: author-email
Dynamic: description
Dynamic: description-content-type
Dynamic: home-page
Dynamic: keywords
Dynamic: license
Dynamic: requires-dist
Dynamic: summary
